{
  "generated_at": "2026-04-23T19:27:14.908448+00:00",
  "n_cells_total": 46,
  "n_cells_rated": 26,
  "medal_counts": {
    "unrated": 20,
    "silver": 16,
    "gold": 9,
    "bronze": 1
  },
  "totals": {
    "n_fired_all": 5238,
    "n_blocked_all": 0,
    "retrain_queue_open": 0
  },
  "cells": [
    {
      "cell_key": "DynamicEngine3|whipsaw|lunch",
      "strategy": "DynamicEngine3",
      "regime": "whipsaw",
      "time_bucket": "lunch",
      "medal": "gold",
      "n_signals": 71,
      "n_fired": 71,
      "n_blocked": 0,
      "purity": 0.7183,
      "cash": 15.46,
      "velocity": 0.1111,
      "purity_rank": 1,
      "cash_rank": 1,
      "velocity_rank": 2,
      "scored_at": "2026-04-23T19:27:14.862165+00:00"
    },
    {
      "cell_key": "DynamicEngine3|dead_tape|overnight",
      "strategy": "DynamicEngine3",
      "regime": "dead_tape",
      "time_bucket": "overnight",
      "medal": "gold",
      "n_signals": 251,
      "n_fired": 251,
      "n_blocked": 0,
      "purity": 0.7012,
      "cash": 9.11,
      "velocity": 0.0086,
      "purity_rank": 2,
      "cash_rank": 2,
      "velocity_rank": 25,
      "scored_at": "2026-04-23T19:27:14.862165+00:00"
    },
    {
      "cell_key": "DynamicEngine3|dead_tape|afternoon",
      "strategy": "DynamicEngine3",
      "regime": "dead_tape",
      "time_bucket": "afternoon",
      "medal": "gold",
      "n_signals": 23,
      "n_fired": 23,
      "n_blocked": 0,
      "purity": 0.6087,
      "cash": 5.67,
      "velocity": 0.0105,
      "purity_rank": 5,
      "cash_rank": 3,
      "velocity_rank": 23,
      "scored_at": "2026-04-23T19:27:14.862165+00:00"
    },
    {
      "cell_key": "DynamicEngine3|neutral|overnight",
      "strategy": "DynamicEngine3",
      "regime": "neutral",
      "time_bucket": "overnight",
      "medal": "gold",
      "n_signals": 173,
      "n_fired": 173,
      "n_blocked": 0,
      "purity": 0.6474,
      "cash": 4.95,
      "velocity": 0.025,
      "purity_rank": 3,
      "cash_rank": 4,
      "velocity_rank": 20,
      "scored_at": "2026-04-23T19:27:14.862165+00:00"
    },
    {
      "cell_key": "DynamicEngine3|calm_trend|overnight",
      "strategy": "DynamicEngine3",
      "regime": "calm_trend",
      "time_bucket": "overnight",
      "medal": "gold",
      "n_signals": 319,
      "n_fired": 319,
      "n_blocked": 0,
      "purity": 0.6207,
      "cash": 4.37,
      "velocity": 0.0256,
      "purity_rank": 4,
      "cash_rank": 5,
      "velocity_rank": 19,
      "scored_at": "2026-04-23T19:27:14.862165+00:00"
    },
    {
      "cell_key": "DynamicEngine3|whipsaw|morning",
      "strategy": "DynamicEngine3",
      "regime": "whipsaw",
      "time_bucket": "morning",
      "medal": "gold",
      "n_signals": 192,
      "n_fired": 192,
      "n_blocked": 0,
      "purity": 0.5,
      "cash": 1.14,
      "velocity": 0.1111,
      "purity_rank": 17,
      "cash_rank": 14,
      "velocity_rank": 3,
      "scored_at": "2026-04-23T19:27:14.862165+00:00"
    },
    {
      "cell_key": "DynamicEngine3|neutral|morning",
      "strategy": "DynamicEngine3",
      "regime": "neutral",
      "time_bucket": "morning",
      "medal": "gold",
      "n_signals": 466,
      "n_fired": 466,
      "n_blocked": 0,
      "purity": 0.5,
      "cash": 0.23,
      "velocity": 0.0909,
      "purity_rank": 16,
      "cash_rank": 15,
      "velocity_rank": 5,
      "scored_at": "2026-04-23T19:27:14.862165+00:00"
    },
    {
      "cell_key": "RegimeAdaptive|calm_trend|overnight",
      "strategy": "RegimeAdaptive",
      "regime": "calm_trend",
      "time_bucket": "overnight",
      "medal": "gold",
      "n_signals": 80,
      "n_fired": 80,
      "n_blocked": 0,
      "purity": 0.3875,
      "cash": -1.53,
      "velocity": 0.1429,
      "purity_rank": 23,
      "cash_rank": 20,
      "velocity_rank": 1,
      "scored_at": "2026-04-23T19:27:14.862165+00:00"
    },
    {
      "cell_key": "DynamicEngine3|calm_trend|lunch",
      "strategy": "DynamicEngine3",
      "regime": "calm_trend",
      "time_bucket": "lunch",
      "medal": "gold",
      "n_signals": 368,
      "n_fired": 368,
      "n_blocked": 0,
      "purity": 0.4946,
      "cash": -4.91,
      "velocity": 0.0909,
      "purity_rank": 18,
      "cash_rank": 25,
      "velocity_rank": 4,
      "scored_at": "2026-04-23T19:27:14.862165+00:00"
    },
    {
      "cell_key": "DynamicEngine3|dead_tape|pre_open",
      "strategy": "DynamicEngine3",
      "regime": "dead_tape",
      "time_bucket": "pre_open",
      "medal": "silver",
      "n_signals": 227,
      "n_fired": 227,
      "n_blocked": 0,
      "purity": 0.5947,
      "cash": 4.35,
      "velocity": 0.0093,
      "purity_rank": 6,
      "cash_rank": 6,
      "velocity_rank": 24,
      "scored_at": "2026-04-23T19:27:14.862165+00:00"
    },
    {
      "cell_key": "DynamicEngine3|neutral|afternoon",
      "strategy": "DynamicEngine3",
      "regime": "neutral",
      "time_bucket": "afternoon",
      "medal": "silver",
      "n_signals": 153,
      "n_fired": 153,
      "n_blocked": 0,
      "purity": 0.5425,
      "cash": 4.18,
      "velocity": 0.0476,
      "purity_rank": 9,
      "cash_rank": 7,
      "velocity_rank": 15,
      "scored_at": "2026-04-23T19:27:14.862165+00:00"
    },
    {
      "cell_key": "DynamicEngine3|whipsaw|pre_open",
      "strategy": "DynamicEngine3",
      "regime": "whipsaw",
      "time_bucket": "pre_open",
      "medal": "silver",
      "n_signals": 43,
      "n_fired": 43,
      "n_blocked": 0,
      "purity": 0.5349,
      "cash": 3.88,
      "velocity": 0.0833,
      "purity_rank": 10,
      "cash_rank": 8,
      "velocity_rank": 8,
      "scored_at": "2026-04-23T19:27:14.862165+00:00"
    },
    {
      "cell_key": "DynamicEngine3|calm_trend|morning",
      "strategy": "DynamicEngine3",
      "regime": "calm_trend",
      "time_bucket": "morning",
      "medal": "silver",
      "n_signals": 782,
      "n_fired": 782,
      "n_blocked": 0,
      "purity": 0.5192,
      "cash": 2.62,
      "velocity": 0.0769,
      "purity_rank": 13,
      "cash_rank": 9,
      "velocity_rank": 10,
      "scored_at": "2026-04-23T19:27:14.862165+00:00"
    },
    {
      "cell_key": "DynamicEngine3|dead_tape|morning",
      "strategy": "DynamicEngine3",
      "regime": "dead_tape",
      "time_bucket": "morning",
      "medal": "silver",
      "n_signals": 26,
      "n_fired": 26,
      "n_blocked": 0,
      "purity": 0.4231,
      "cash": 2.56,
      "velocity": 0.0161,
      "purity_rank": 21,
      "cash_rank": 10,
      "velocity_rank": 21,
      "scored_at": "2026-04-23T19:27:14.862165+00:00"
    },
    {
      "cell_key": "DynamicEngine3|calm_trend|post_close",
      "strategy": "DynamicEngine3",
      "regime": "calm_trend",
      "time_bucket": "post_close",
      "medal": "silver",
      "n_signals": 81,
      "n_fired": 81,
      "n_blocked": 0,
      "purity": 0.5062,
      "cash": 2.39,
      "velocity": 0.0122,
      "purity_rank": 15,
      "cash_rank": 11,
      "velocity_rank": 22,
      "scored_at": "2026-04-23T19:27:14.862165+00:00"
    },
    {
      "cell_key": "DynamicEngine3|neutral|post_close",
      "strategy": "DynamicEngine3",
      "regime": "neutral",
      "time_bucket": "post_close",
      "medal": "silver",
      "n_signals": 47,
      "n_fired": 47,
      "n_blocked": 0,
      "purity": 0.5106,
      "cash": 2.08,
      "velocity": 0.0079,
      "purity_rank": 14,
      "cash_rank": 12,
      "velocity_rank": 26,
      "scored_at": "2026-04-23T19:27:14.862165+00:00"
    },
    {
      "cell_key": "RegimeAdaptive|dead_tape|pre_open",
      "strategy": "RegimeAdaptive",
      "regime": "dead_tape",
      "time_bucket": "pre_open",
      "medal": "silver",
      "n_signals": 148,
      "n_fired": 148,
      "n_blocked": 0,
      "purity": 0.4257,
      "cash": 1.54,
      "velocity": 0.0357,
      "purity_rank": 20,
      "cash_rank": 13,
      "velocity_rank": 18,
      "scored_at": "2026-04-23T19:27:14.862165+00:00"
    },
    {
      "cell_key": "DynamicEngine3|neutral|pre_open",
      "strategy": "DynamicEngine3",
      "regime": "neutral",
      "time_bucket": "pre_open",
      "medal": "silver",
      "n_signals": 298,
      "n_fired": 298,
      "n_blocked": 0,
      "purity": 0.5638,
      "cash": -0.05,
      "velocity": 0.0417,
      "purity_rank": 8,
      "cash_rank": 16,
      "velocity_rank": 17,
      "scored_at": "2026-04-23T19:27:14.862165+00:00"
    },
    {
      "cell_key": "RegimeAdaptive|neutral|overnight",
      "strategy": "RegimeAdaptive",
      "regime": "neutral",
      "time_bucket": "overnight",
      "medal": "silver",
      "n_signals": 88,
      "n_fired": 88,
      "n_blocked": 0,
      "purity": 0.375,
      "cash": -0.63,
      "velocity": 0.0833,
      "purity_rank": 25,
      "cash_rank": 17,
      "velocity_rank": 9,
      "scored_at": "2026-04-23T19:27:14.862165+00:00"
    },
    {
      "cell_key": "DynamicEngine3|whipsaw|afternoon",
      "strategy": "DynamicEngine3",
      "regime": "whipsaw",
      "time_bucket": "afternoon",
      "medal": "silver",
      "n_signals": 40,
      "n_fired": 40,
      "n_blocked": 0,
      "purity": 0.525,
      "cash": -0.8,
      "velocity": 0.0909,
      "purity_rank": 12,
      "cash_rank": 18,
      "velocity_rank": 6,
      "scored_at": "2026-04-23T19:27:14.862165+00:00"
    },
    {
      "cell_key": "RegimeAdaptive|calm_trend|pre_open",
      "strategy": "RegimeAdaptive",
      "regime": "calm_trend",
      "time_bucket": "pre_open",
      "medal": "silver",
      "n_signals": 119,
      "n_fired": 119,
      "n_blocked": 0,
      "purity": 0.4202,
      "cash": -0.84,
      "velocity": 0.0909,
      "purity_rank": 22,
      "cash_rank": 19,
      "velocity_rank": 7,
      "scored_at": "2026-04-23T19:27:14.862165+00:00"
    },
    {
      "cell_key": "RegimeAdaptive|neutral|pre_open",
      "strategy": "RegimeAdaptive",
      "regime": "neutral",
      "time_bucket": "pre_open",
      "medal": "silver",
      "n_signals": 151,
      "n_fired": 151,
      "n_blocked": 0,
      "purity": 0.3841,
      "cash": -2.22,
      "velocity": 0.0667,
      "purity_rank": 24,
      "cash_rank": 22,
      "velocity_rank": 12,
      "scored_at": "2026-04-23T19:27:14.862165+00:00"
    },
    {
      "cell_key": "DynamicEngine3|neutral|lunch",
      "strategy": "DynamicEngine3",
      "regime": "neutral",
      "time_bucket": "lunch",
      "medal": "silver",
      "n_signals": 197,
      "n_fired": 197,
      "n_blocked": 0,
      "purity": 0.5838,
      "cash": -2.61,
      "velocity": 0.0556,
      "purity_rank": 7,
      "cash_rank": 23,
      "velocity_rank": 13,
      "scored_at": "2026-04-23T19:27:14.862165+00:00"
    },
    {
      "cell_key": "DynamicEngine3|calm_trend|pre_open",
      "strategy": "DynamicEngine3",
      "regime": "calm_trend",
      "time_bucket": "pre_open",
      "medal": "silver",
      "n_signals": 387,
      "n_fired": 387,
      "n_blocked": 0,
      "purity": 0.5323,
      "cash": -3.23,
      "velocity": 0.0526,
      "purity_rank": 11,
      "cash_rank": 24,
      "velocity_rank": 14,
      "scored_at": "2026-04-23T19:27:14.862165+00:00"
    },
    {
      "cell_key": "DynamicEngine3|calm_trend|afternoon",
      "strategy": "DynamicEngine3",
      "regime": "calm_trend",
      "time_bucket": "afternoon",
      "medal": "silver",
      "n_signals": 249,
      "n_fired": 249,
      "n_blocked": 0,
      "purity": 0.4819,
      "cash": -5.2,
      "velocity": 0.0667,
      "purity_rank": 19,
      "cash_rank": 26,
      "velocity_rank": 11,
      "scored_at": "2026-04-23T19:27:14.862165+00:00"
    },
    {
      "cell_key": "RegimeAdaptive|dead_tape|overnight",
      "strategy": "RegimeAdaptive",
      "regime": "dead_tape",
      "time_bucket": "overnight",
      "medal": "bronze",
      "n_signals": 119,
      "n_fired": 119,
      "n_blocked": 0,
      "purity": 0.3025,
      "cash": -1.85,
      "velocity": 0.0455,
      "purity_rank": 26,
      "cash_rank": 21,
      "velocity_rank": 16,
      "scored_at": "2026-04-23T19:27:14.862165+00:00"
    },
    {
      "cell_key": "AetherFlow|calm_trend|afternoon",
      "strategy": "AetherFlow",
      "regime": "calm_trend",
      "time_bucket": "afternoon",
      "medal": "unrated",
      "n_signals": 2,
      "n_fired": 2,
      "n_blocked": 0,
      "purity": null,
      "cash": null,
      "velocity": null,
      "purity_rank": null,
      "cash_rank": null,
      "velocity_rank": null,
      "scored_at": "2026-04-23T19:27:14.862165+00:00"
    },
    {
      "cell_key": "AetherFlow|calm_trend|lunch",
      "strategy": "AetherFlow",
      "regime": "calm_trend",
      "time_bucket": "lunch",
      "medal": "unrated",
      "n_signals": 5,
      "n_fired": 5,
      "n_blocked": 0,
      "purity": null,
      "cash": null,
      "velocity": null,
      "purity_rank": null,
      "cash_rank": null,
      "velocity_rank": null,
      "scored_at": "2026-04-23T19:27:14.862165+00:00"
    },
    {
      "cell_key": "AetherFlow|calm_trend|morning",
      "strategy": "AetherFlow",
      "regime": "calm_trend",
      "time_bucket": "morning",
      "medal": "unrated",
      "n_signals": 14,
      "n_fired": 14,
      "n_blocked": 0,
      "purity": null,
      "cash": null,
      "velocity": null,
      "purity_rank": null,
      "cash_rank": null,
      "velocity_rank": null,
      "scored_at": "2026-04-23T19:27:14.862165+00:00"
    },
    {
      "cell_key": "AetherFlow|calm_trend|overnight",
      "strategy": "AetherFlow",
      "regime": "calm_trend",
      "time_bucket": "overnight",
      "medal": "unrated",
      "n_signals": 1,
      "n_fired": 1,
      "n_blocked": 0,
      "purity": null,
      "cash": null,
      "velocity": null,
      "purity_rank": null,
      "cash_rank": null,
      "velocity_rank": null,
      "scored_at": "2026-04-23T19:27:14.862165+00:00"
    },
    {
      "cell_key": "AetherFlow|calm_trend|post_close",
      "strategy": "AetherFlow",
      "regime": "calm_trend",
      "time_bucket": "post_close",
      "medal": "unrated",
      "n_signals": 18,
      "n_fired": 18,
      "n_blocked": 0,
      "purity": null,
      "cash": null,
      "velocity": null,
      "purity_rank": null,
      "cash_rank": null,
      "velocity_rank": null,
      "scored_at": "2026-04-23T19:27:14.862165+00:00"
    },
    {
      "cell_key": "AetherFlow|calm_trend|pre_open",
      "strategy": "AetherFlow",
      "regime": "calm_trend",
      "time_bucket": "pre_open",
      "medal": "unrated",
      "n_signals": 2,
      "n_fired": 2,
      "n_blocked": 0,
      "purity": null,
      "cash": null,
      "velocity": null,
      "purity_rank": null,
      "cash_rank": null,
      "velocity_rank": null,
      "scored_at": "2026-04-23T19:27:14.862165+00:00"
    },
    {
      "cell_key": "AetherFlow|neutral|afternoon",
      "strategy": "AetherFlow",
      "regime": "neutral",
      "time_bucket": "afternoon",
      "medal": "unrated",
      "n_signals": 1,
      "n_fired": 1,
      "n_blocked": 0,
      "purity": null,
      "cash": null,
      "velocity": null,
      "purity_rank": null,
      "cash_rank": null,
      "velocity_rank": null,
      "scored_at": "2026-04-23T19:27:14.862165+00:00"
    },
    {
      "cell_key": "AetherFlow|neutral|lunch",
      "strategy": "AetherFlow",
      "regime": "neutral",
      "time_bucket": "lunch",
      "medal": "unrated",
      "n_signals": 3,
      "n_fired": 3,
      "n_blocked": 0,
      "purity": null,
      "cash": null,
      "velocity": null,
      "purity_rank": null,
      "cash_rank": null,
      "velocity_rank": null,
      "scored_at": "2026-04-23T19:27:14.862165+00:00"
    },
    {
      "cell_key": "AetherFlow|neutral|morning",
      "strategy": "AetherFlow",
      "regime": "neutral",
      "time_bucket": "morning",
      "medal": "unrated",
      "n_signals": 4,
      "n_fired": 4,
      "n_blocked": 0,
      "purity": null,
      "cash": null,
      "velocity": null,
      "purity_rank": null,
      "cash_rank": null,
      "velocity_rank": null,
      "scored_at": "2026-04-23T19:27:14.862165+00:00"
    },
    {
      "cell_key": "AetherFlow|neutral|post_close",
      "strategy": "AetherFlow",
      "regime": "neutral",
      "time_bucket": "post_close",
      "medal": "unrated",
      "n_signals": 12,
      "n_fired": 12,
      "n_blocked": 0,
      "purity": null,
      "cash": null,
      "velocity": null,
      "purity_rank": null,
      "cash_rank": null,
      "velocity_rank": null,
      "scored_at": "2026-04-23T19:27:14.862165+00:00"
    },
    {
      "cell_key": "AetherFlow|whipsaw|lunch",
      "strategy": "AetherFlow",
      "regime": "whipsaw",
      "time_bucket": "lunch",
      "medal": "unrated",
      "n_signals": 3,
      "n_fired": 3,
      "n_blocked": 0,
      "purity": null,
      "cash": null,
      "velocity": null,
      "purity_rank": null,
      "cash_rank": null,
      "velocity_rank": null,
      "scored_at": "2026-04-23T19:27:14.862165+00:00"
    },
    {
      "cell_key": "AetherFlow|whipsaw|morning",
      "strategy": "AetherFlow",
      "regime": "whipsaw",
      "time_bucket": "morning",
      "medal": "unrated",
      "n_signals": 3,
      "n_fired": 3,
      "n_blocked": 0,
      "purity": null,
      "cash": null,
      "velocity": null,
      "purity_rank": null,
      "cash_rank": null,
      "velocity_rank": null,
      "scored_at": "2026-04-23T19:27:14.862165+00:00"
    },
    {
      "cell_key": "AetherFlow|whipsaw|post_close",
      "strategy": "AetherFlow",
      "regime": "whipsaw",
      "time_bucket": "post_close",
      "medal": "unrated",
      "n_signals": 3,
      "n_fired": 3,
      "n_blocked": 0,
      "purity": null,
      "cash": null,
      "velocity": null,
      "purity_rank": null,
      "cash_rank": null,
      "velocity_rank": null,
      "scored_at": "2026-04-23T19:27:14.862165+00:00"
    },
    {
      "cell_key": "AetherFlow|whipsaw|pre_open",
      "strategy": "AetherFlow",
      "regime": "whipsaw",
      "time_bucket": "pre_open",
      "medal": "unrated",
      "n_signals": 1,
      "n_fired": 1,
      "n_blocked": 0,
      "purity": null,
      "cash": null,
      "velocity": null,
      "purity_rank": null,
      "cash_rank": null,
      "velocity_rank": null,
      "scored_at": "2026-04-23T19:27:14.862165+00:00"
    },
    {
      "cell_key": "DynamicEngine3|dead_tape|lunch",
      "strategy": "DynamicEngine3",
      "regime": "dead_tape",
      "time_bucket": "lunch",
      "medal": "unrated",
      "n_signals": 17,
      "n_fired": 17,
      "n_blocked": 0,
      "purity": null,
      "cash": null,
      "velocity": null,
      "purity_rank": null,
      "cash_rank": null,
      "velocity_rank": null,
      "scored_at": "2026-04-23T19:27:14.862165+00:00"
    },
    {
      "cell_key": "DynamicEngine3|dead_tape|post_close",
      "strategy": "DynamicEngine3",
      "regime": "dead_tape",
      "time_bucket": "post_close",
      "medal": "unrated",
      "n_signals": 11,
      "n_fired": 11,
      "n_blocked": 0,
      "purity": null,
      "cash": null,
      "velocity": null,
      "purity_rank": null,
      "cash_rank": null,
      "velocity_rank": null,
      "scored_at": "2026-04-23T19:27:14.862165+00:00"
    },
    {
      "cell_key": "DynamicEngine3|whipsaw|overnight",
      "strategy": "DynamicEngine3",
      "regime": "whipsaw",
      "time_bucket": "overnight",
      "medal": "unrated",
      "n_signals": 13,
      "n_fired": 13,
      "n_blocked": 0,
      "purity": null,
      "cash": null,
      "velocity": null,
      "purity_rank": null,
      "cash_rank": null,
      "velocity_rank": null,
      "scored_at": "2026-04-23T19:27:14.862165+00:00"
    },
    {
      "cell_key": "DynamicEngine3|whipsaw|post_close",
      "strategy": "DynamicEngine3",
      "regime": "whipsaw",
      "time_bucket": "post_close",
      "medal": "unrated",
      "n_signals": 19,
      "n_fired": 19,
      "n_blocked": 0,
      "purity": null,
      "cash": null,
      "velocity": null,
      "purity_rank": null,
      "cash_rank": null,
      "velocity_rank": null,
      "scored_at": "2026-04-23T19:27:14.862165+00:00"
    },
    {
      "cell_key": "RegimeAdaptive|whipsaw|overnight",
      "strategy": "RegimeAdaptive",
      "regime": "whipsaw",
      "time_bucket": "overnight",
      "medal": "unrated",
      "n_signals": 4,
      "n_fired": 4,
      "n_blocked": 0,
      "purity": null,
      "cash": null,
      "velocity": null,
      "purity_rank": null,
      "cash_rank": null,
      "velocity_rank": null,
      "scored_at": "2026-04-23T19:27:14.862165+00:00"
    },
    {
      "cell_key": "RegimeAdaptive|whipsaw|pre_open",
      "strategy": "RegimeAdaptive",
      "regime": "whipsaw",
      "time_bucket": "pre_open",
      "medal": "unrated",
      "n_signals": 4,
      "n_fired": 4,
      "n_blocked": 0,
      "purity": null,
      "cash": null,
      "velocity": null,
      "purity_rank": null,
      "cash_rank": null,
      "velocity_rank": null,
      "scored_at": "2026-04-23T19:27:14.862165+00:00"
    }
  ],
  "recent_signals": [
    {
      "signal_id": "aeec9a27-6f22-4935-a2e5-277272298888",
      "ts": "2026-04-23T19:23:00.476908+00:00",
      "strategy": "DynamicEngine3",
      "side": "LONG",
      "regime": "neutral",
      "time_bucket": "morning",
      "status": "fired",
      "block_filter": null,
      "block_reason": null,
      "entry_price": 7135.5,
      "size": 3,
      "pnl_dollars": 125.5,
      "exit_source": "take",
      "counterfactual": 0
    }
  ],
  "retrain_queue": []
}